dataplex_sm_cli/__init__.py
dataplex_sm_cli/cli.py
dataplex_sm_cli/validator.js
dataplex_sm_cli-0.2.1.dist-info/METADATA
dataplex_sm_cli-0.2.1.dist-info/WHEEL
dataplex_sm_cli-0.2.1.dist-info/entry_points.txt
dataplex_sm_cli-0.2.1.dist-info/top_level.txt
dataplex_sm_cli-0.2.1.dist-info/RECORD
