Metadata-Version: 2.4
Name: dataplex-sm-cli
Version: 0.2.1
Summary: A CLI tool for Dataplex Semantic Model operations with YAML validation
Home-page: https://github.com/Sachin-Rungta/dataplex-sm-cli
Author: Sachin Rungta
Author-email: Sachin Rungta <sachin.rungta@example.com>
License: MIT
Keywords: cli,dataplex,semantic-model
Classifier: Development Status :: 3 - Alpha
Classifier: Intended Audience :: Developers
Classifier: License :: OSI Approved :: MIT License
Classifier: Programming Language :: Python :: 3
Classifier: Programming Language :: Python :: 3.8
Classifier: Programming Language :: Python :: 3.9
Classifier: Programming Language :: Python :: 3.10
Classifier: Programming Language :: Python :: 3.11
Requires-Python: >=3.8
Requires-Dist: click>=8.0.0
Provides-Extra: dev
Requires-Dist: pytest>=7.0; extra == "dev"
Requires-Dist: pytest-cov>=4.0; extra == "dev"
Requires-Dist: black>=22.0; extra == "dev"
Requires-Dist: flake8>=4.0; extra == "dev"
Requires-Dist: mypy>=0.950; extra == "dev"
Dynamic: author
Dynamic: home-page
Dynamic: requires-python
